polly_read/__init__.py
polly_read/ssml_builder.py
polly_read/txt_to_ssml.py
polly_read-0.0.1.dist-info/DESCRIPTION.rst
polly_read-0.0.1.dist-info/METADATA
polly_read-0.0.1.dist-info/RECORD
polly_read-0.0.1.dist-info/WHEEL
polly_read-0.0.1.dist-info/entry_points.txt
polly_read-0.0.1.dist-info/metadata.json
polly_read-0.0.1.dist-info/top_level.txt
