Metadata-Version: 2.0
Name: polly-read
Version: 0.0.1
Summary: another fcm wrapper in python
Home-page: https://github.com/jiamo/polly_read
Author: jiamo
Author-email: life.130815@gmail.com
License: MIT
Keywords: polly_read
Platform: UNKNOWN
Classifier: Development Status :: 2 - Pre-Alpha
Classifier: Intended Audience :: Developers
Classifier: Natural Language :: English
Classifier: Programming Language :: Python :: 3.6
Requires-Dist: click (>=6.0)
Requires-Dist: google-api-python-client (>=1.6.4)
Requires-Dist: oauth2client (>=4.1.2)
Requires-Dist: requests
Requires-Dist: PyYAML
